erdammer/__init__.py
erdammer/cli.py
erdammer/dot.py
erdammer/main.py
erdammer/models.py
erdammer/transformers.py
erdammer/version.py
erdammer-0.0.5.dist-info/DESCRIPTION.rst
erdammer-0.0.5.dist-info/entry_points.txt
erdammer-0.0.5.dist-info/METADATA
erdammer-0.0.5.dist-info/metadata.json
erdammer-0.0.5.dist-info/RECORD
erdammer-0.0.5.dist-info/top_level.txt
erdammer-0.0.5.dist-info/WHEEL
