Metadata-Version: 2.0
Name: erdammer
Version: 0.0.5
Summary: Simple tool to generate database schema documentation
Home-page: https://github.com/vranac/erdammer
Author: Srdjan Vranac
Author-email: vranac@gmail.com
License: MIT
Keywords: erdammer
Platform: UNKNOWN
Classifier: Development Status :: 3 - Alpha
Classifier: Intended Audience :: Developers
Classifier: License :: OSI Approved :: MIT License
Classifier: Natural Language :: English
Classifier: Programming Language :: Python :: 2
Classifier: Programming Language :: Python :: 2.6
Classifier: Programming Language :: Python :: 2.7
Requires-Dist: SQLAlchemy (==1.0.12)
Requires-Dist: click (==6.6)
Requires-Dist: mysql-connector-python-rf (==2.0.4)
Requires-Dist: pygraphviz (==1.3.1)
